py_session/__init__.py
py_session/py_session.py
py_session-0.1.0.dist-info/METADATA
py_session-0.1.0.dist-info/RECORD
py_session-0.1.0.dist-info/WHEEL
py_session-0.1.0.dist-info/top_level.txt
