Metadata-Version: 2.1
Name: py-session
Version: 0.1.0
Summary: Print session information
Home-page: https://github.com/fbrundu/py_session
Author: Francesco G. Brundu
Author-email: francesco.brundu@gmail.com
License: MIT license
Keywords: py_session
Platform: UNKNOWN
Classifier: Development Status :: 2 - Pre-Alpha
Classifier: Intended Audience :: Developers
Classifier: License :: OSI Approved :: MIT License
Classifier: Natural Language :: English
Classifier: Programming Language :: Python :: 2
Classifier: Programming Language :: Python :: 2.7
Classifier: Programming Language :: Python :: 3
Classifier: Programming Language :: Python :: 3.4
Classifier: Programming Language :: Python :: 3.5
Classifier: Programming Language :: Python :: 3.6
